.gitignore
.travis.yml
README.rst
pylintrc
requirements.txt
setup.cfg
setup.py
test_requirements.txt
tox.ini
piprun/__init__.py
piprun.egg-info/PKG-INFO
piprun.egg-info/SOURCES.txt
piprun.egg-info/dependency_links.txt
piprun.egg-info/entry_points.txt
piprun.egg-info/requires.txt
piprun.egg-info/top_level.txt
tests/__init__.py
tests/base.py
tests/test_piprun.py
tests/test_tests.py