Metadata-Version: 1.1
Name: piprun
Version: 0.0.6
Summary: Specify scripts' PyPI dependencies inline
Home-page: https://github.com/koterpillar/piprun
Author: Alexey Kotlyarov
Author-email: a@koterpillar.com
License: UNKNOWN
Platform: UNKNOWN
Classifier: License :: OSI Approved :: GNU General Public License v3 or later (GPLv3+)
Classifier: Programming Language :: Python
Classifier: Programming Language :: Python :: 2
Classifier: Programming Language :: Python :: 3
